exhaustive_weighted_random_sampler/__init__.py
exhaustive_weighted_random_sampler-0.0.2.dist-info/LICENSE
exhaustive_weighted_random_sampler-0.0.2.dist-info/METADATA
exhaustive_weighted_random_sampler-0.0.2.dist-info/WHEEL
exhaustive_weighted_random_sampler-0.0.2.dist-info/top_level.txt
exhaustive_weighted_random_sampler-0.0.2.dist-info/RECORD
